public_google_sheets_backup/__init__.py
public_google_sheets_backup/cli.py
public_google_sheets_backup/core.py
public_google_sheets_backup-1.0.0.dist-info/licenses/LICENSE
public_google_sheets_backup-1.0.0.dist-info/METADATA
public_google_sheets_backup-1.0.0.dist-info/WHEEL
public_google_sheets_backup-1.0.0.dist-info/entry_points.txt
public_google_sheets_backup-1.0.0.dist-info/top_level.txt
public_google_sheets_backup-1.0.0.dist-info/RECORD
